mcp_mysql/__init__.py
mcp_mysql/__main__.py
mcp_mysql/server.py
mcp_mysql-0.1.1.dist-info/METADATA
mcp_mysql-0.1.1.dist-info/WHEEL
mcp_mysql-0.1.1.dist-info/entry_points.txt
mcp_mysql-0.1.1.dist-info/RECORD
