Metadata-Version: 2.4
Name: mcp_mysql
Version: 0.1.1
Summary: MCP MySQL Server
Author: Your Name
Requires-Python: >=3.10
Requires-Dist: mcp[cli]
Requires-Dist: pymysql
